MANIFEST.in
VERSION.txt
requirements.txt
setup.py
maas/__init__.py
maas/admin.py
maas/apps.py
maas/exceptions.py
maas/models.py
maas/views.py
maas.egg-info/PKG-INFO
maas.egg-info/SOURCES.txt
maas.egg-info/dependency_links.txt
maas.egg-info/not-zip-safe
maas.egg-info/top_level.txt
maas/migrations/0001_initial.py
maas/migrations/0002_auto_20170606_1857.py
maas/migrations/0003_auto_20170606_1928.py
maas/migrations/0004_auto_20170606_2017.py
maas/migrations/0005_mailevent.py
maas/migrations/__init__.py
maas/tests/__init__.py
maas/tests/test_generic.py
maas/tests/test_mailgun.py
project/__init__.py
project/context_processors.py
project/settings.py
project/urls.py
project/wsgi.py