Metadata-Version: 1.0
Name: maas
Version: 1.3.2
Summary: Django wrapper for interfacing with e-Mail as a Service providers.
Home-page: https://gitlab.com/matix-io/django-maas
Author: Connor Bode
Author-email: connor@matix.io
License: BSD
Platform: UNKNOWN
